prompts/full-prompt.txt
prompts/update-prompt.txt
readme_writer/__init__.py
readme_writer/cli.py
readme_writer/config.py
readme_writer/core.py
readme_writer/diff_analyzer.py
readme_writer/file_processor.py
readme_writer/openai_client.py
readme_writer/prompt_loader.py
readme_writer-1.0.10.dist-info/METADATA
readme_writer-1.0.10.dist-info/WHEEL
readme_writer-1.0.10.dist-info/entry_points.txt
readme_writer-1.0.10.dist-info/top_level.txt
readme_writer-1.0.10.dist-info/RECORD
