Metadata-Version: 2.4
Name: readme-writer
Version: 1.0.10
Summary: AI-powered documentation generator for Git repositories using OpenAI API
Author: Readme generator
License-Expression: MIT
Keywords: documentation,readme,ai,openai,git
Classifier: Intended Audience :: Developers
Classifier: Programming Language :: Python :: 3
Classifier: Topic :: Documentation
Classifier: Topic :: Software Development :: Documentation
Requires-Python: >=3.8
Requires-Dist: openai>=1.0.0
Requires-Dist: click>=8.0.0
Requires-Dist: tiktoken>=0.5.0
Requires-Dist: rich>=13.0.0
Requires-Dist: pyyaml>=6.0
Requires-Dist: jinja2>=3.0.0
